poetry_new_project/__init__.py
poetry_new_project/app.py
poetry_new_project-0.1.1.dist-info/entry_points.txt
poetry_new_project-0.1.1.dist-info/LICENSE
poetry_new_project-0.1.1.dist-info/WHEEL
poetry_new_project-0.1.1.dist-info/METADATA
poetry_new_project-0.1.1.dist-info/RECORD
