Metadata-Version: 2.1
Name: poetry-new-project
Version: 0.1.1
Summary: 
Author: Zach Bellay
Author-email: zachbellay@hotmail.com
Requires-Python: >=3.9,<4.0
Classifier: Programming Language :: Python :: 3
Classifier: Programming Language :: Python :: 3.9
Classifier: Programming Language :: Python :: 3.10
Requires-Dist: click (>=8.1.3,<9.0.0)
